AutoPypline/__init__.py
AutoPypline/auto_pipeline.py
AutoPypline/Utils/__init__.py
AutoPypline/Utils/utils.py
AutoPypline/_auto_pipeline_backend/__init__.py
AutoPypline/_auto_pipeline_backend/_designer.py
AutoPypline/_auto_pipeline_backend/_execution_utils.py
AutoPypline/_auto_pipeline_backend/_executor.py
AutoPypline/_auto_pipeline_backend/_flow_preparation.py
AutoPypline/_auto_pipeline_backend/_other_utils.py
AutoPypline/_auto_pipeline_backend/_sample_generator_related.py
test_scripts/__init__.py
test_scripts/arithmetic.py
test_scripts/random_generators.py
test_scripts/sample_generators.py
test_scripts/value_processors.py
AutoPypline-1.0.4.dist-info/LICENSE
AutoPypline-1.0.4.dist-info/METADATA
AutoPypline-1.0.4.dist-info/WHEEL
AutoPypline-1.0.4.dist-info/top_level.txt
AutoPypline-1.0.4.dist-info/RECORD
