Metadata-Version: 2.1
Name: AutoPypline
Version: 1.0.4
Summary: A package for automating python pipelines
Home-page: https://github.com/Sumukha21/AutoPypline
Author: Sumukha Manjunath
Author-email: sumukha1996@gmail.com
License: UNKNOWN
Platform: UNKNOWN
Classifier: Programming Language :: Python :: 3
Classifier: License :: OSI Approved :: MIT License
Classifier: Operating System :: OS Independent
